trained-model.bin
autosubsync/__init__.py
autosubsync/features.py
autosubsync/find_transform.py
autosubsync/main.py
autosubsync/model.py
autosubsync/predict.py
autosubsync/preprocessing.py
autosubsync/quality_of_fit.py
autosubsync/srt_io.py
autosubsync/trained_logistic_regression.py
autosubsync-1.0.1.dist-info/LICENSE.txt
autosubsync-1.0.1.dist-info/METADATA
autosubsync-1.0.1.dist-info/WHEEL
autosubsync-1.0.1.dist-info/entry_points.txt
autosubsync-1.0.1.dist-info/top_level.txt
autosubsync-1.0.1.dist-info/RECORD
