Metadata-Version: 2.1
Name: autosubsync
Version: 1.0.1
Summary: Automatically synchronize subtitles with audio
Home-page: https://github.com/oseiskar/autosubsync
Author: Otto Seiskari
License: MIT
Keywords: subtitles syncrhonization srt ffmpeg
Platform: UNKNOWN
Classifier: Development Status :: 5 - Production/Stable
Classifier: Environment :: Console
Classifier: Operating System :: POSIX
Classifier: Intended Audience :: End Users/Desktop
Classifier: Topic :: Multimedia
Classifier: License :: OSI Approved :: MIT License
Classifier: Programming Language :: Python :: 2
Classifier: Programming Language :: Python :: 3
Requires-Dist: numpy
Requires-Dist: pysoundfile
Provides-Extra: dev
Requires-Dist: pandas ; extra == 'dev'
Requires-Dist: scikit-learn ; extra == 'dev'
